aas_middleware/__init__.py
aas_middleware/connect/__init__.py
aas_middleware/connect/connectors/__init__.py
aas_middleware/connect/connectors/aas_client_connector/__init__.py
aas_middleware/connect/connectors/aas_client_connector/aas_client.py
aas_middleware/connect/connectors/aas_client_connector/aas_client_caching_connector.py
aas_middleware/connect/connectors/aas_client_connector/aas_client_connector.py
aas_middleware/connect/connectors/aas_client_connector/aas_client_model.py
aas_middleware/connect/connectors/aas_client_connector/client_utils.py
aas_middleware/connect/connectors/aas_client_connector/submodel_client.py
aas_middleware/connect/connectors/async_connector.py
aas_middleware/connect/connectors/connector.py
aas_middleware/connect/connectors/http_polling_connector.py
aas_middleware/connect/connectors/http_request_connector.py
aas_middleware/connect/connectors/http_request_connector_auth.py
aas_middleware/connect/connectors/model_connector.py
aas_middleware/connect/connectors/mqtt_client_connector.py
aas_middleware/connect/connectors/opc_ua_client_connector.py
aas_middleware/connect/connectors/web_hook_client_connector.py
aas_middleware/connect/connectors/web_hook_server_connector.py
aas_middleware/connect/connectors/web_socket_client_connector.py
aas_middleware/connect/connectors/web_socket_server_connector.py
aas_middleware/connect/workflows/blocking_workflow.py
aas_middleware/connect/workflows/queuing_workflow.py
aas_middleware/connect/workflows/worfklow_description.py
aas_middleware/connect/workflows/workflow.py
aas_middleware/middleware/__init__.py
aas_middleware/middleware/aas_persistence_middleware.py
aas_middleware/middleware/connector_router.py
aas_middleware/middleware/graphql_routers.py
aas_middleware/middleware/middleware.py
aas_middleware/middleware/model_registry_api.py
aas_middleware/middleware/persistence_factory.py
aas_middleware/middleware/registries.py
aas_middleware/middleware/rest_routers.py
aas_middleware/middleware/sync/__init__.py
aas_middleware-0.2.6.dist-info/LICENSE
aas_middleware-0.2.6.dist-info/METADATA
aas_middleware-0.2.6.dist-info/WHEEL
aas_middleware-0.2.6.dist-info/RECORD
