Metadata-Version: 2.1
Name: aas-middleware
Version: 0.2.6
Summary: 
Author: Sebastian Behrendt
Author-email: sebastianbehrendt97@gmail.com
Requires-Python: >=3.10,<4.0
Classifier: Programming Language :: Python :: 3
Classifier: Programming Language :: Python :: 3.10
Classifier: Programming Language :: Python :: 3.11
Provides-Extra: industrial
Requires-Dist: aas-pydantic (>=0.1.2,<0.2.0)
Requires-Dist: aiohttp (>=3.10.11,<4.0.0)
Requires-Dist: aiomqtt (>=2.1.0,<3.0.0) ; extra == "industrial"
Requires-Dist: anyio (>=4.3.0,<5.0.0)
Requires-Dist: asyncua (>=1.1.0,<2.0.0) ; extra == "industrial"
Requires-Dist: ba-syx-aas-environment-component-client (>=2.1,<3.0)
Requires-Dist: basyx-python-sdk (>=1.0.0,<2.0.0)
Requires-Dist: datamodel-code-generator (>=0.25.6,<0.26.0)
Requires-Dist: exceptiongroup (>=1.2.2,<2.0.0)
Requires-Dist: fastapi (>=0.111.0,<0.112.0)
Requires-Dist: graphene-pydantic (>=0.6.1,<0.7.0)
Requires-Dist: importlib-metadata (>=8.0.0,<9.0.0)
Requires-Dist: mkdocstrings[python-legacy] (>=0.25.1,<0.26.0)
Requires-Dist: pydantic (>=2.7.1,<3.0.0)
Requires-Dist: starlette-graphene3 (>=0.6.0,<0.7.0)
Requires-Dist: toml (>=0.10.2,<0.11.0)
Requires-Dist: typeguard (>=4.4.1,<5.0.0)
Requires-Dist: uvicorn (>=0.29.0,<0.30.0)
